{
    "configurations": [
        {
            "name": "Win32",
            "includePath": [
                "${workspaceFolder}/**",
                "C:/msys64/ucrt64/include/c++/15.2.0",
                "C:/msys64/ucrt64/include/c++/15.2.0/x86_64-w64-mingw32",
                "C:/msys64/ucrt64/include"
            ],
            "defines": [
                "_DEBUG",
                "UNICODE",
                "_UNICODE"
            ],
            "compilerPath": "C:/msys64/ucrt64/bin/g++.exe",
            "cStandard": "c17",
            "cppStandard": "c++20",
            "intelliSenseMode": "windows-gcc-x64"
        }
    ],
    "version": 4
}
